{
  "version": "6",
  "dialect": "sqlite",
  "id": "f81d7b89-f4ed-4dd6-b7d3-5619f7efe315",
  "prevId": "aa10c992-851d-4757-a515-e1cea51ba9fb",
  "tables": {
    "audit_logs": {
      "name": "audit_logs",
      "columns": {
        "id": {
          "name": "id",
          "type": "text",
          "primaryKey": true,
          "notNull": true,
          "autoincrement": false
        },
        "user_id": {
          "name": "user_id",
          "type": "text",
          "primaryKey": false,
          "notNull": true,
          "autoincrement": false
        },
        "action": {
          "name": "action",
          "type": "text",
          "primaryKey": false,
          "notNull": true,
          "autoincrement": false
        },
        "target_type": {
          "name": "target_type",
          "type": "text",
          "primaryKey": false,
          "notNull": true,
          "autoincrement": false
        },
        "target_id": {
          "name": "target_id",
          "type": "text",
          "primaryKey": false,
          "notNull": true,
          "autoincrement": false
        },
        "metadata": {
          "name": "metadata",
          "type": "text",
          "primaryKey": false,
          "notNull": false,
          "autoincrement": false
        },
        "ip_address": {
          "name": "ip_address",
          "type": "text",
          "primaryKey": false,
          "notNull": false,
          "autoincrement": false
        },
        "created_at": {
          "name": "created_at",
          "type": "integer",
          "primaryKey": false,
          "notNull": true,
          "autoincrement": false
        }
      },
      "indexes": {
        "audit_logs_user_idx": {
          "name": "audit_logs_user_idx",
          "columns": [
            "user_id"
          ],
          "isUnique": false
        },
        "audit_logs_target_idx": {
          "name": "audit_logs_target_idx",
          "columns": [
            "target_type",
            "target_id"
          ],
          "isUnique": false
        },
        "audit_logs_created_idx": {
          "name": "audit_logs_created_idx",
          "columns": [
            "created_at"
          ],
          "isUnique": false
        }
      },
      "foreignKeys": {
        "audit_logs_user_id_users_id_fk": {
          "name": "audit_logs_user_id_users_id_fk",
          "tableFrom": "audit_logs",
          "tableTo": "users",
          "columnsFrom": [
            "user_id"
          ],
          "columnsTo": [
            "id"
          ],
          "onDelete": "no action",
          "onUpdate": "no action"
        }
      },
      "compositePrimaryKeys": {},
      "uniqueConstraints": {},
      "checkConstraints": {}
    },
    "comments": {
      "name": "comments",
      "columns": {
        "id": {
          "name": "id",
          "type": "text",
          "primaryKey": true,
          "notNull": true,
          "autoincrement": false
        },
        "author_id": {
          "name": "author_id",
          "type": "text",
          "primaryKey": false,
          "notNull": true,
          "autoincrement": false
        },
        "body": {
          "name": "body",
          "type": "text",
          "primaryKey": false,
          "notNull": true,
          "autoincrement": false
        },
        "pull_request_id": {
          "name": "pull_request_id",
          "type": "text",
          "primaryKey": false,
          "notNull": false,
          "autoincrement": false
        },
        "issue_id": {
          "name": "issue_id",
          "type": "text",
          "primaryKey": false,
          "notNull": false,
          "autoincrement": false
        },
        "created_at": {
          "name": "created_at",
          "type": "integer",
          "primaryKey": false,
          "notNull": true,
          "autoincrement": false
        },
        "updated_at": {
          "name": "updated_at",
          "type": "integer",
          "primaryKey": false,
          "notNull": true,
          "autoincrement": false
        }
      },
      "indexes": {},
      "foreignKeys": {
        "comments_author_id_users_id_fk": {
          "name": "comments_author_id_users_id_fk",
          "tableFrom": "comments",
          "tableTo": "users",
          "columnsFrom": [
            "author_id"
          ],
          "columnsTo": [
            "id"
          ],
          "onDelete": "no action",
          "onUpdate": "no action"
        },
        "comments_pull_request_id_pull_requests_id_fk": {
          "name": "comments_pull_request_id_pull_requests_id_fk",
          "tableFrom": "comments",
          "tableTo": "pull_requests",
          "columnsFrom": [
            "pull_request_id"
          ],
          "columnsTo": [
            "id"
          ],
          "onDelete": "cascade",
          "onUpdate": "no action"
        },
        "comments_issue_id_issues_id_fk": {
          "name": "comments_issue_id_issues_id_fk",
          "tableFrom": "comments",
          "tableTo": "issues",
          "columnsFrom": [
            "issue_id"
          ],
          "columnsTo": [
            "id"
          ],
          "onDelete": "cascade",
          "onUpdate": "no action"
        }
      },
      "compositePrimaryKeys": {},
      "uniqueConstraints": {},
      "checkConstraints": {}
    },
    "edit_history": {
      "name": "edit_history",
      "columns": {
        "id": {
          "name": "id",
          "type": "text",
          "primaryKey": true,
          "notNull": true,
          "autoincrement": false
        },
        "issue_id": {
          "name": "issue_id",
          "type": "text",
          "primaryKey": false,
          "notNull": false,
          "autoincrement": false
        },
        "pull_request_id": {
          "name": "pull_request_id",
          "type": "text",
          "primaryKey": false,
          "notNull": false,
          "autoincrement": false
        },
        "comment_id": {
          "name": "comment_id",
          "type": "text",
          "primaryKey": false,
          "notNull": false,
          "autoincrement": false
        },
        "target_type": {
          "name": "target_type",
          "type": "text",
          "primaryKey": false,
          "notNull": true,
          "autoincrement": false
        },
        "previous_title": {
          "name": "previous_title",
          "type": "text",
          "primaryKey": false,
          "notNull": false,
          "autoincrement": false
        },
        "previous_body": {
          "name": "previous_body",
          "type": "text",
          "primaryKey": false,
          "notNull": false,
          "autoincrement": false
        },
        "edited_by_id": {
          "name": "edited_by_id",
          "type": "text",
          "primaryKey": false,
          "notNull": true,
          "autoincrement": false
        },
        "created_at": {
          "name": "created_at",
          "type": "integer",
          "primaryKey": false,
          "notNull": true,
          "autoincrement": false
        }
      },
      "indexes": {},
      "foreignKeys": {
        "edit_history_issue_id_issues_id_fk": {
          "name": "edit_history_issue_id_issues_id_fk",
          "tableFrom": "edit_history",
          "tableTo": "issues",
          "columnsFrom": [
            "issue_id"
          ],
          "columnsTo": [
            "id"
          ],
          "onDelete": "cascade",
          "onUpdate": "no action"
        },
        "edit_history_pull_request_id_pull_requests_id_fk": {
          "name": "edit_history_pull_request_id_pull_requests_id_fk",
          "tableFrom": "edit_history",
          "tableTo": "pull_requests",
          "columnsFrom": [
            "pull_request_id"
          ],
          "columnsTo": [
            "id"
          ],
          "onDelete": "cascade",
          "onUpdate": "no action"
        },
        "edit_history_comment_id_comments_id_fk": {
          "name": "edit_history_comment_id_comments_id_fk",
          "tableFrom": "edit_history",
          "tableTo": "comments",
          "columnsFrom": [
            "comment_id"
          ],
          "columnsTo": [
            "id"
          ],
          "onDelete": "cascade",
          "onUpdate": "no action"
        },
        "edit_history_edited_by_id_users_id_fk": {
          "name": "edit_history_edited_by_id_users_id_fk",
          "tableFrom": "edit_history",
          "tableTo": "users",
          "columnsFrom": [
            "edited_by_id"
          ],
          "columnsTo": [
            "id"
          ],
          "onDelete": "no action",
          "onUpdate": "no action"
        }
      },
      "compositePrimaryKeys": {},
      "uniqueConstraints": {},
      "checkConstraints": {}
    },
    "git_blobs": {
      "name": "git_blobs",
      "columns": {
        "id": {
          "name": "id",
          "type": "text",
          "primaryKey": true,
          "notNull": true,
          "autoincrement": false
        },
        "repo_id": {
          "name": "repo_id",
          "type": "text",
          "primaryKey": false,
          "notNull": true,
          "autoincrement": false
        },
        "oid": {
          "name": "oid",
          "type": "text",
          "primaryKey": false,
          "notNull": true,
          "autoincrement": false
        },
        "content": {
          "name": "content",
          "type": "text",
          "primaryKey": false,
          "notNull": false,
          "autoincrement": false
        },
        "size": {
          "name": "size",
          "type": "integer",
          "primaryKey": false,
          "notNull": true,
          "autoincrement": false
        },
        "is_binary": {
          "name": "is_binary",
          "type": "integer",
          "primaryKey": false,
          "notNull": true,
          "autoincrement": false,
          "default": false
        },
        "is_truncated": {
          "name": "is_truncated",
          "type": "integer",
          "primaryKey": false,
          "notNull": true,
          "autoincrement": false,
          "default": false
        }
      },
      "indexes": {
        "git_blobs_repo_oid_idx": {
          "name": "git_blobs_repo_oid_idx",
          "columns": [
            "repo_id",
            "oid"
          ],
          "isUnique": true
        }
      },
      "foreignKeys": {
        "git_blobs_repo_id_repositories_id_fk": {
          "name": "git_blobs_repo_id_repositories_id_fk",
          "tableFrom": "git_blobs",
          "tableTo": "repositories",
          "columnsFrom": [
            "repo_id"
          ],
          "columnsTo": [
            "id"
          ],
          "onDelete": "cascade",
          "onUpdate": "no action"
        }
      },
      "compositePrimaryKeys": {},
      "uniqueConstraints": {},
      "checkConstraints": {}
    },
    "git_commit_ancestry": {
      "name": "git_commit_ancestry",
      "columns": {
        "id": {
          "name": "id",
          "type": "text",
          "primaryKey": true,
          "notNull": true,
          "autoincrement": false
        },
        "repo_id": {
          "name": "repo_id",
          "type": "text",
          "primaryKey": false,
          "notNull": true,
          "autoincrement": false
        },
        "ref_name": {
          "name": "ref_name",
          "type": "text",
          "primaryKey": false,
          "notNull": true,
          "autoincrement": false
        },
        "commit_oid": {
          "name": "commit_oid",
          "type": "text",
          "primaryKey": false,
          "notNull": true,
          "autoincrement": false
        },
        "depth": {
          "name": "depth",
          "type": "integer",
          "primaryKey": false,
          "notNull": true,
          "autoincrement": false
        }
      },
      "indexes": {
        "git_ancestry_repo_ref_commit_idx": {
          "name": "git_ancestry_repo_ref_commit_idx",
          "columns": [
            "repo_id",
            "ref_name",
            "commit_oid"
          ],
          "isUnique": true
        },
        "git_ancestry_repo_ref_depth_idx": {
          "name": "git_ancestry_repo_ref_depth_idx",
          "columns": [
            "repo_id",
            "ref_name",
            "depth"
          ],
          "isUnique": false
        }
      },
      "foreignKeys": {
        "git_commit_ancestry_repo_id_repositories_id_fk": {
          "name": "git_commit_ancestry_repo_id_repositories_id_fk",
          "tableFrom": "git_commit_ancestry",
          "tableTo": "repositories",
          "columnsFrom": [
            "repo_id"
          ],
          "columnsTo": [
            "id"
          ],
          "onDelete": "cascade",
          "onUpdate": "no action"
        }
      },
      "compositePrimaryKeys": {},
      "uniqueConstraints": {},
      "checkConstraints": {}
    },
    "git_commit_files": {
      "name": "git_commit_files",
      "columns": {
        "id": {
          "name": "id",
          "type": "text",
          "primaryKey": true,
          "notNull": true,
          "autoincrement": false
        },
        "repo_id": {
          "name": "repo_id",
          "type": "text",
          "primaryKey": false,
          "notNull": true,
          "autoincrement": false
        },
        "commit_oid": {
          "name": "commit_oid",
          "type": "text",
          "primaryKey": false,
          "notNull": true,
          "autoincrement": false
        },
        "file_path": {
          "name": "file_path",
          "type": "text",
          "primaryKey": false,
          "notNull": true,
          "autoincrement": false
        },
        "change_type": {
          "name": "change_type",
          "type": "text",
          "primaryKey": false,
          "notNull": true,
          "autoincrement": false
        }
      },
      "indexes": {
        "git_commit_files_repo_commit_path_idx": {
          "name": "git_commit_files_repo_commit_path_idx",
          "columns": [
            "repo_id",
            "commit_oid",
            "file_path"
          ],
          "isUnique": true
        },
        "git_commit_files_repo_path_idx": {
          "name": "git_commit_files_repo_path_idx",
          "columns": [
            "repo_id",
            "file_path"
          ],
          "isUnique": false
        }
      },
      "foreignKeys": {
        "git_commit_files_repo_id_repositories_id_fk": {
          "name": "git_commit_files_repo_id_repositories_id_fk",
          "tableFrom": "git_commit_files",
          "tableTo": "repositories",
          "columnsFrom": [
            "repo_id"
          ],
          "columnsTo": [
            "id"
          ],
          "onDelete": "cascade",
          "onUpdate": "no action"
        }
      },
      "compositePrimaryKeys": {},
      "uniqueConstraints": {},
      "checkConstraints": {}
    },
    "git_commits": {
      "name": "git_commits",
      "columns": {
        "id": {
          "name": "id",
          "type": "text",
          "primaryKey": true,
          "notNull": true,
          "autoincrement": false
        },
        "repo_id": {
          "name": "repo_id",
          "type": "text",
          "primaryKey": false,
          "notNull": true,
          "autoincrement": false
        },
        "oid": {
          "name": "oid",
          "type": "text",
          "primaryKey": false,
          "notNull": true,
          "autoincrement": false
        },
        "message": {
          "name": "message",
          "type": "text",
          "primaryKey": false,
          "notNull": true,
          "autoincrement": false
        },
        "author_name": {
          "name": "author_name",
          "type": "text",
          "primaryKey": false,
          "notNull": true,
          "autoincrement": false
        },
        "author_email": {
          "name": "author_email",
          "type": "text",
          "primaryKey": false,
          "notNull": true,
          "autoincrement": false
        },
        "author_timestamp": {
          "name": "author_timestamp",
          "type": "integer",
          "primaryKey": false,
          "notNull": true,
          "autoincrement": false
        },
        "committer_name": {
          "name": "committer_name",
          "type": "text",
          "primaryKey": false,
          "notNull": true,
          "autoincrement": false
        },
        "committer_email": {
          "name": "committer_email",
          "type": "text",
          "primaryKey": false,
          "notNull": true,
          "autoincrement": false
        },
        "committer_timestamp": {
          "name": "committer_timestamp",
          "type": "integer",
          "primaryKey": false,
          "notNull": true,
          "autoincrement": false
        },
        "parent_oids": {
          "name": "parent_oids",
          "type": "text",
          "primaryKey": false,
          "notNull": true,
          "autoincrement": false,
          "default": "'[]'"
        },
        "tree_oid": {
          "name": "tree_oid",
          "type": "text",
          "primaryKey": false,
          "notNull": true,
          "autoincrement": false
        }
      },
      "indexes": {
        "git_commits_repo_oid_idx": {
          "name": "git_commits_repo_oid_idx",
          "columns": [
            "repo_id",
            "oid"
          ],
          "isUnique": true
        }
      },
      "foreignKeys": {
        "git_commits_repo_id_repositories_id_fk": {
          "name": "git_commits_repo_id_repositories_id_fk",
          "tableFrom": "git_commits",
          "tableTo": "repositories",
          "columnsFrom": [
            "repo_id"
          ],
          "columnsTo": [
            "id"
          ],
          "onDelete": "cascade",
          "onUpdate": "no action"
        }
      },
      "compositePrimaryKeys": {},
      "uniqueConstraints": {},
      "checkConstraints": {}
    },
    "git_refs": {
      "name": "git_refs",
      "columns": {
        "id": {
          "name": "id",
          "type": "text",
          "primaryKey": true,
          "notNull": true,
          "autoincrement": false
        },
        "repo_id": {
          "name": "repo_id",
          "type": "text",
          "primaryKey": false,
          "notNull": true,
          "autoincrement": false
        },
        "name": {
          "name": "name",
          "type": "text",
          "primaryKey": false,
          "notNull": true,
          "autoincrement": false
        },
        "type": {
          "name": "type",
          "type": "text",
          "primaryKey": false,
          "notNull": true,
          "autoincrement": false
        },
        "commit_oid": {
          "name": "commit_oid",
          "type": "text",
          "primaryKey": false,
          "notNull": true,
          "autoincrement": false
        },
        "updated_at": {
          "name": "updated_at",
          "type": "integer",
          "primaryKey": false,
          "notNull": true,
          "autoincrement": false
        }
      },
      "indexes": {
        "git_refs_repo_name_idx": {
          "name": "git_refs_repo_name_idx",
          "columns": [
            "repo_id",
            "name"
          ],
          "isUnique": true
        }
      },
      "foreignKeys": {
        "git_refs_repo_id_repositories_id_fk": {
          "name": "git_refs_repo_id_repositories_id_fk",
          "tableFrom": "git_refs",
          "tableTo": "repositories",
          "columnsFrom": [
            "repo_id"
          ],
          "columnsTo": [
            "id"
          ],
          "onDelete": "cascade",
          "onUpdate": "no action"
        }
      },
      "compositePrimaryKeys": {},
      "uniqueConstraints": {},
      "checkConstraints": {}
    },
    "git_tree_entries": {
      "name": "git_tree_entries",
      "columns": {
        "id": {
          "name": "id",
          "type": "text",
          "primaryKey": true,
          "notNull": true,
          "autoincrement": false
        },
        "repo_id": {
          "name": "repo_id",
          "type": "text",
          "primaryKey": false,
          "notNull": true,
          "autoincrement": false
        },
        "root_tree_oid": {
          "name": "root_tree_oid",
          "type": "text",
          "primaryKey": false,
          "notNull": true,
          "autoincrement": false
        },
        "parent_path": {
          "name": "parent_path",
          "type": "text",
          "primaryKey": false,
          "notNull": true,
          "autoincrement": false
        },
        "entry_name": {
          "name": "entry_name",
          "type": "text",
          "primaryKey": false,
          "notNull": true,
          "autoincrement": false
        },
        "entry_path": {
          "name": "entry_path",
          "type": "text",
          "primaryKey": false,
          "notNull": true,
          "autoincrement": false
        },
        "entry_type": {
          "name": "entry_type",
          "type": "text",
          "primaryKey": false,
          "notNull": true,
          "autoincrement": false
        },
        "entry_oid": {
          "name": "entry_oid",
          "type": "text",
          "primaryKey": false,
          "notNull": true,
          "autoincrement": false
        },
        "entry_size": {
          "name": "entry_size",
          "type": "integer",
          "primaryKey": false,
          "notNull": false,
          "autoincrement": false
        }
      },
      "indexes": {
        "git_tree_entry_tree_path_idx": {
          "name": "git_tree_entry_tree_path_idx",
          "columns": [
            "repo_id",
            "root_tree_oid",
            "entry_path"
          ],
          "isUnique": true
        },
        "git_tree_entry_listing_idx": {
          "name": "git_tree_entry_listing_idx",
          "columns": [
            "repo_id",
            "root_tree_oid",
            "parent_path"
          ],
          "isUnique": false
        }
      },
      "foreignKeys": {
        "git_tree_entries_repo_id_repositories_id_fk": {
          "name": "git_tree_entries_repo_id_repositories_id_fk",
          "tableFrom": "git_tree_entries",
          "tableTo": "repositories",
          "columnsFrom": [
            "repo_id"
          ],
          "columnsTo": [
            "id"
          ],
          "onDelete": "cascade",
          "onUpdate": "no action"
        }
      },
      "compositePrimaryKeys": {},
      "uniqueConstraints": {},
      "checkConstraints": {}
    },
    "issues": {
      "name": "issues",
      "columns": {
        "id": {
          "name": "id",
          "type": "text",
          "primaryKey": true,
          "notNull": true,
          "autoincrement": false
        },
        "number": {
          "name": "number",
          "type": "integer",
          "primaryKey": false,
          "notNull": true,
          "autoincrement": false
        },
        "repo_id": {
          "name": "repo_id",
          "type": "text",
          "primaryKey": false,
          "notNull": true,
          "autoincrement": false
        },
        "title": {
          "name": "title",
          "type": "text",
          "primaryKey": false,
          "notNull": true,
          "autoincrement": false
        },
        "body": {
          "name": "body",
          "type": "text",
          "primaryKey": false,
          "notNull": false,
          "autoincrement": false
        },
        "author_id": {
          "name": "author_id",
          "type": "text",
          "primaryKey": false,
          "notNull": true,
          "autoincrement": false
        },
        "status": {
          "name": "status",
          "type": "text",
          "primaryKey": false,
          "notNull": true,
          "autoincrement": false,
          "default": "'open'"
        },
        "created_at": {
          "name": "created_at",
          "type": "integer",
          "primaryKey": false,
          "notNull": true,
          "autoincrement": false
        },
        "updated_at": {
          "name": "updated_at",
          "type": "integer",
          "primaryKey": false,
          "notNull": true,
          "autoincrement": false
        },
        "closed_at": {
          "name": "closed_at",
          "type": "integer",
          "primaryKey": false,
          "notNull": false,
          "autoincrement": false
        }
      },
      "indexes": {},
      "foreignKeys": {
        "issues_repo_id_repositories_id_fk": {
          "name": "issues_repo_id_repositories_id_fk",
          "tableFrom": "issues",
          "tableTo": "repositories",
          "columnsFrom": [
            "repo_id"
          ],
          "columnsTo": [
            "id"
          ],
          "onDelete": "cascade",
          "onUpdate": "no action"
        },
        "issues_author_id_users_id_fk": {
          "name": "issues_author_id_users_id_fk",
          "tableFrom": "issues",
          "tableTo": "users",
          "columnsFrom": [
            "author_id"
          ],
          "columnsTo": [
            "id"
          ],
          "onDelete": "no action",
          "onUpdate": "no action"
        }
      },
      "compositePrimaryKeys": {},
      "uniqueConstraints": {},
      "checkConstraints": {}
    },
    "personal_access_tokens": {
      "name": "personal_access_tokens",
      "columns": {
        "id": {
          "name": "id",
          "type": "text",
          "primaryKey": true,
          "notNull": true,
          "autoincrement": false
        },
        "user_id": {
          "name": "user_id",
          "type": "text",
          "primaryKey": false,
          "notNull": true,
          "autoincrement": false
        },
        "name": {
          "name": "name",
          "type": "text",
          "primaryKey": false,
          "notNull": true,
          "autoincrement": false
        },
        "token_hash": {
          "name": "token_hash",
          "type": "text",
          "primaryKey": false,
          "notNull": true,
          "autoincrement": false
        },
        "token_prefix": {
          "name": "token_prefix",
          "type": "text",
          "primaryKey": false,
          "notNull": true,
          "autoincrement": false
        },
        "scopes": {
          "name": "scopes",
          "type": "text",
          "primaryKey": false,
          "notNull": true,
          "autoincrement": false,
          "default": "'[\"repo\",\"user\"]'"
        },
        "expires_at": {
          "name": "expires_at",
          "type": "integer",
          "primaryKey": false,
          "notNull": false,
          "autoincrement": false
        },
        "last_used_at": {
          "name": "last_used_at",
          "type": "integer",
          "primaryKey": false,
          "notNull": false,
          "autoincrement": false
        },
        "created_at": {
          "name": "created_at",
          "type": "integer",
          "primaryKey": false,
          "notNull": true,
          "autoincrement": false
        }
      },
      "indexes": {
        "pat_user_idx": {
          "name": "pat_user_idx",
          "columns": [
            "user_id"
          ],
          "isUnique": false
        },
        "pat_hash_idx": {
          "name": "pat_hash_idx",
          "columns": [
            "token_hash"
          ],
          "isUnique": true
        }
      },
      "foreignKeys": {
        "personal_access_tokens_user_id_users_id_fk": {
          "name": "personal_access_tokens_user_id_users_id_fk",
          "tableFrom": "personal_access_tokens",
          "tableTo": "users",
          "columnsFrom": [
            "user_id"
          ],
          "columnsTo": [
            "id"
          ],
          "onDelete": "cascade",
          "onUpdate": "no action"
        }
      },
      "compositePrimaryKeys": {},
      "uniqueConstraints": {},
      "checkConstraints": {}
    },
    "pull_requests": {
      "name": "pull_requests",
      "columns": {
        "id": {
          "name": "id",
          "type": "text",
          "primaryKey": true,
          "notNull": true,
          "autoincrement": false
        },
        "number": {
          "name": "number",
          "type": "integer",
          "primaryKey": false,
          "notNull": true,
          "autoincrement": false
        },
        "repo_id": {
          "name": "repo_id",
          "type": "text",
          "primaryKey": false,
          "notNull": true,
          "autoincrement": false
        },
        "title": {
          "name": "title",
          "type": "text",
          "primaryKey": false,
          "notNull": true,
          "autoincrement": false
        },
        "body": {
          "name": "body",
          "type": "text",
          "primaryKey": false,
          "notNull": false,
          "autoincrement": false
        },
        "author_id": {
          "name": "author_id",
          "type": "text",
          "primaryKey": false,
          "notNull": true,
          "autoincrement": false
        },
        "source_branch": {
          "name": "source_branch",
          "type": "text",
          "primaryKey": false,
          "notNull": true,
          "autoincrement": false
        },
        "target_branch": {
          "name": "target_branch",
          "type": "text",
          "primaryKey": false,
          "notNull": true,
          "autoincrement": false
        },
        "status": {
          "name": "status",
          "type": "text",
          "primaryKey": false,
          "notNull": true,
          "autoincrement": false,
          "default": "'open'"
        },
        "created_at": {
          "name": "created_at",
          "type": "integer",
          "primaryKey": false,
          "notNull": true,
          "autoincrement": false
        },
        "updated_at": {
          "name": "updated_at",
          "type": "integer",
          "primaryKey": false,
          "notNull": true,
          "autoincrement": false
        },
        "merged_at": {
          "name": "merged_at",
          "type": "integer",
          "primaryKey": false,
          "notNull": false,
          "autoincrement": false
        },
        "merged_by_id": {
          "name": "merged_by_id",
          "type": "text",
          "primaryKey": false,
          "notNull": false,
          "autoincrement": false
        }
      },
      "indexes": {},
      "foreignKeys": {
        "pull_requests_repo_id_repositories_id_fk": {
          "name": "pull_requests_repo_id_repositories_id_fk",
          "tableFrom": "pull_requests",
          "tableTo": "repositories",
          "columnsFrom": [
            "repo_id"
          ],
          "columnsTo": [
            "id"
          ],
          "onDelete": "cascade",
          "onUpdate": "no action"
        },
        "pull_requests_author_id_users_id_fk": {
          "name": "pull_requests_author_id_users_id_fk",
          "tableFrom": "pull_requests",
          "tableTo": "users",
          "columnsFrom": [
            "author_id"
          ],
          "columnsTo": [
            "id"
          ],
          "onDelete": "no action",
          "onUpdate": "no action"
        },
        "pull_requests_merged_by_id_users_id_fk": {
          "name": "pull_requests_merged_by_id_users_id_fk",
          "tableFrom": "pull_requests",
          "tableTo": "users",
          "columnsFrom": [
            "merged_by_id"
          ],
          "columnsTo": [
            "id"
          ],
          "onDelete": "no action",
          "onUpdate": "no action"
        }
      },
      "compositePrimaryKeys": {},
      "uniqueConstraints": {},
      "checkConstraints": {}
    },
    "repo_collaborators": {
      "name": "repo_collaborators",
      "columns": {
        "id": {
          "name": "id",
          "type": "text",
          "primaryKey": true,
          "notNull": true,
          "autoincrement": false
        },
        "repo_id": {
          "name": "repo_id",
          "type": "text",
          "primaryKey": false,
          "notNull": true,
          "autoincrement": false
        },
        "user_id": {
          "name": "user_id",
          "type": "text",
          "primaryKey": false,
          "notNull": true,
          "autoincrement": false
        },
        "permission": {
          "name": "permission",
          "type": "text",
          "primaryKey": false,
          "notNull": true,
          "autoincrement": false,
          "default": "'write'"
        },
        "created_at": {
          "name": "created_at",
          "type": "integer",
          "primaryKey": false,
          "notNull": true,
          "autoincrement": false
        }
      },
      "indexes": {
        "collab_repo_user_idx": {
          "name": "collab_repo_user_idx",
          "columns": [
            "repo_id",
            "user_id"
          ],
          "isUnique": true
        }
      },
      "foreignKeys": {
        "repo_collaborators_repo_id_repositories_id_fk": {
          "name": "repo_collaborators_repo_id_repositories_id_fk",
          "tableFrom": "repo_collaborators",
          "tableTo": "repositories",
          "columnsFrom": [
            "repo_id"
          ],
          "columnsTo": [
            "id"
          ],
          "onDelete": "cascade",
          "onUpdate": "no action"
        },
        "repo_collaborators_user_id_users_id_fk": {
          "name": "repo_collaborators_user_id_users_id_fk",
          "tableFrom": "repo_collaborators",
          "tableTo": "users",
          "columnsFrom": [
            "user_id"
          ],
          "columnsTo": [
            "id"
          ],
          "onDelete": "cascade",
          "onUpdate": "no action"
        }
      },
      "compositePrimaryKeys": {},
      "uniqueConstraints": {},
      "checkConstraints": {}
    },
    "repositories": {
      "name": "repositories",
      "columns": {
        "id": {
          "name": "id",
          "type": "text",
          "primaryKey": true,
          "notNull": true,
          "autoincrement": false
        },
        "owner_id": {
          "name": "owner_id",
          "type": "text",
          "primaryKey": false,
          "notNull": true,
          "autoincrement": false
        },
        "name": {
          "name": "name",
          "type": "text",
          "primaryKey": false,
          "notNull": true,
          "autoincrement": false
        },
        "description": {
          "name": "description",
          "type": "text",
          "primaryKey": false,
          "notNull": false,
          "autoincrement": false
        },
        "default_branch": {
          "name": "default_branch",
          "type": "text",
          "primaryKey": false,
          "notNull": true,
          "autoincrement": false,
          "default": "'main'"
        },
        "is_public": {
          "name": "is_public",
          "type": "integer",
          "primaryKey": false,
          "notNull": true,
          "autoincrement": false,
          "default": true
        },
        "disk_path": {
          "name": "disk_path",
          "type": "text",
          "primaryKey": false,
          "notNull": true,
          "autoincrement": false
        },
        "created_at": {
          "name": "created_at",
          "type": "integer",
          "primaryKey": false,
          "notNull": true,
          "autoincrement": false
        },
        "updated_at": {
          "name": "updated_at",
          "type": "integer",
          "primaryKey": false,
          "notNull": true,
          "autoincrement": false
        }
      },
      "indexes": {
        "repo_owner_name_idx": {
          "name": "repo_owner_name_idx",
          "columns": [
            "owner_id",
            "name"
          ],
          "isUnique": true
        }
      },
      "foreignKeys": {
        "repositories_owner_id_users_id_fk": {
          "name": "repositories_owner_id_users_id_fk",
          "tableFrom": "repositories",
          "tableTo": "users",
          "columnsFrom": [
            "owner_id"
          ],
          "columnsTo": [
            "id"
          ],
          "onDelete": "cascade",
          "onUpdate": "no action"
        }
      },
      "compositePrimaryKeys": {},
      "uniqueConstraints": {},
      "checkConstraints": {}
    },
    "sessions": {
      "name": "sessions",
      "columns": {
        "id": {
          "name": "id",
          "type": "text",
          "primaryKey": true,
          "notNull": true,
          "autoincrement": false
        },
        "user_id": {
          "name": "user_id",
          "type": "text",
          "primaryKey": false,
          "notNull": true,
          "autoincrement": false
        },
        "token": {
          "name": "token",
          "type": "text",
          "primaryKey": false,
          "notNull": true,
          "autoincrement": false
        },
        "expires_at": {
          "name": "expires_at",
          "type": "integer",
          "primaryKey": false,
          "notNull": true,
          "autoincrement": false
        },
        "created_at": {
          "name": "created_at",
          "type": "integer",
          "primaryKey": false,
          "notNull": true,
          "autoincrement": false
        }
      },
      "indexes": {
        "sessions_token_unique": {
          "name": "sessions_token_unique",
          "columns": [
            "token"
          ],
          "isUnique": true
        }
      },
      "foreignKeys": {
        "sessions_user_id_users_id_fk": {
          "name": "sessions_user_id_users_id_fk",
          "tableFrom": "sessions",
          "tableTo": "users",
          "columnsFrom": [
            "user_id"
          ],
          "columnsTo": [
            "id"
          ],
          "onDelete": "cascade",
          "onUpdate": "no action"
        }
      },
      "compositePrimaryKeys": {},
      "uniqueConstraints": {},
      "checkConstraints": {}
    },
    "ssh_keys": {
      "name": "ssh_keys",
      "columns": {
        "id": {
          "name": "id",
          "type": "text",
          "primaryKey": true,
          "notNull": true,
          "autoincrement": false
        },
        "user_id": {
          "name": "user_id",
          "type": "text",
          "primaryKey": false,
          "notNull": true,
          "autoincrement": false
        },
        "title": {
          "name": "title",
          "type": "text",
          "primaryKey": false,
          "notNull": true,
          "autoincrement": false
        },
        "public_key": {
          "name": "public_key",
          "type": "text",
          "primaryKey": false,
          "notNull": true,
          "autoincrement": false
        },
        "fingerprint": {
          "name": "fingerprint",
          "type": "text",
          "primaryKey": false,
          "notNull": true,
          "autoincrement": false
        },
        "created_at": {
          "name": "created_at",
          "type": "integer",
          "primaryKey": false,
          "notNull": true,
          "autoincrement": false
        }
      },
      "indexes": {},
      "foreignKeys": {
        "ssh_keys_user_id_users_id_fk": {
          "name": "ssh_keys_user_id_users_id_fk",
          "tableFrom": "ssh_keys",
          "tableTo": "users",
          "columnsFrom": [
            "user_id"
          ],
          "columnsTo": [
            "id"
          ],
          "onDelete": "cascade",
          "onUpdate": "no action"
        }
      },
      "compositePrimaryKeys": {},
      "uniqueConstraints": {},
      "checkConstraints": {}
    },
    "users": {
      "name": "users",
      "columns": {
        "id": {
          "name": "id",
          "type": "text",
          "primaryKey": true,
          "notNull": true,
          "autoincrement": false
        },
        "username": {
          "name": "username",
          "type": "text",
          "primaryKey": false,
          "notNull": true,
          "autoincrement": false
        },
        "email": {
          "name": "email",
          "type": "text",
          "primaryKey": false,
          "notNull": true,
          "autoincrement": false
        },
        "password_hash": {
          "name": "password_hash",
          "type": "text",
          "primaryKey": false,
          "notNull": true,
          "autoincrement": false
        },
        "display_name": {
          "name": "display_name",
          "type": "text",
          "primaryKey": false,
          "notNull": false,
          "autoincrement": false
        },
        "bio": {
          "name": "bio",
          "type": "text",
          "primaryKey": false,
          "notNull": false,
          "autoincrement": false
        },
        "is_admin": {
          "name": "is_admin",
          "type": "integer",
          "primaryKey": false,
          "notNull": true,
          "autoincrement": false,
          "default": false
        },
        "created_at": {
          "name": "created_at",
          "type": "integer",
          "primaryKey": false,
          "notNull": true,
          "autoincrement": false
        },
        "updated_at": {
          "name": "updated_at",
          "type": "integer",
          "primaryKey": false,
          "notNull": true,
          "autoincrement": false
        }
      },
      "indexes": {
        "users_username_unique": {
          "name": "users_username_unique",
          "columns": [
            "username"
          ],
          "isUnique": true
        },
        "users_email_unique": {
          "name": "users_email_unique",
          "columns": [
            "email"
          ],
          "isUnique": true
        }
      },
      "foreignKeys": {},
      "compositePrimaryKeys": {},
      "uniqueConstraints": {},
      "checkConstraints": {}
    }
  },
  "views": {},
  "enums": {},
  "_meta": {
    "schemas": {},
    "tables": {},
    "columns": {}
  },
  "internal": {
    "indexes": {}
  }
}